hifrost/__init__.py
hifrost-0.0.1.dist-info/DESCRIPTION.rst
hifrost-0.0.1.dist-info/METADATA
hifrost-0.0.1.dist-info/RECORD
hifrost-0.0.1.dist-info/WHEEL
hifrost-0.0.1.dist-info/metadata.json
hifrost-0.0.1.dist-info/top_level.txt
