Metadata-Version: 2.0
Name: hifrost
Version: 0.0.1
Summary: ZaihuiHui Bifrost
Home-page: https://github.com/zaihui
Author: ZaiHui
Author-email: llk@kezaihui.com
License: MIT License
Platform: UNKNOWN
